arcade_asana_api/__init__.py
arcade_asana_api/moar/Asana.json
arcade_asana_api/moar/openapi.json
arcade_asana_api/tools/__init__.py
arcade_asana_api/tools/request_body_schemas.py
arcade_asana_api/wrapper_tools/AddAsanaTask.json
arcade_asana_api/wrapper_tools/AddCustomFieldSettingToProject.json
arcade_asana_api/wrapper_tools/AddCustomFieldToPortfolio.json
arcade_asana_api/wrapper_tools/AddDependentsToTask.json
arcade_asana_api/wrapper_tools/AddEnumOptionToCustomField.json
arcade_asana_api/wrapper_tools/AddFollowersToGoal.json
arcade_asana_api/wrapper_tools/AddFollowersToProject.json
arcade_asana_api/wrapper_tools/AddFollowersToTask.json
arcade_asana_api/wrapper_tools/AddItemToPortfolio.json
arcade_asana_api/wrapper_tools/AddMembersToProject.json
arcade_asana_api/wrapper_tools/AddPortfolioMembers.json
arcade_asana_api/wrapper_tools/AddTagToTask.json
arcade_asana_api/wrapper_tools/AddTaskComment.json
arcade_asana_api/wrapper_tools/AddTaskDependencies.json
arcade_asana_api/wrapper_tools/AddTaskToProject.json
arcade_asana_api/wrapper_tools/AddTaskToSection.json
arcade_asana_api/wrapper_tools/AddUserToTeam.json
arcade_asana_api/wrapper_tools/AddUserToWorkspace.json
arcade_asana_api/wrapper_tools/ApproveAccessRequest.json
arcade_asana_api/wrapper_tools/AsanaCreateTeam.json
arcade_asana_api/wrapper_tools/AsanaDuplicateProject.json
arcade_asana_api/wrapper_tools/AsanaRemoveFollowerForTask.json
arcade_asana_api/wrapper_tools/AsanaUpdateWebhookFilters.json
arcade_asana_api/wrapper_tools/CreateAllocation.json
arcade_asana_api/wrapper_tools/CreateAsanaGoal.json
arcade_asana_api/wrapper_tools/CreateAsanaMembership.json
arcade_asana_api/wrapper_tools/CreateAsanaPortfolio.json
arcade_asana_api/wrapper_tools/CreateAsanaProjectForTeam.json
arcade_asana_api/wrapper_tools/CreateAsanaTask.json
arcade_asana_api/wrapper_tools/CreateAsanaWebhook.json
arcade_asana_api/wrapper_tools/CreateCustomFieldInWorkspace.json
arcade_asana_api/wrapper_tools/CreateGoalMetric.json
arcade_asana_api-1.0.0.dist-info/METADATA
arcade_asana_api-1.0.0.dist-info/WHEEL
arcade_asana_api-1.0.0.dist-info/entry_points.txt
arcade_asana_api-1.0.0.dist-info/RECORD
